{
  "2xx":
  {
    "dayIcon": "cl",
    "nightIcon": "mcl"
  },
  "3xx":
  {
    "dayIcon": "pr",
    "nightIcon": "mcr"
  },
  "5xx":
  {
    "dayIcon": "pr",
    "nightIcon": "mcr"
  },
  "6xx":
  {
    "dayIcon": "cs",
    "nightIcon": "ms"
  },
  "7xx":
  {
    "dayIcon": "c",
    "nightIcon": "c"
  },
  "800":
  {
    "dayIcon": "s",
    "nightIcon": "m"
  },
  "80x":
  {
    "dayIcon": "p",
    "nightIcon": "mc"
  },
  "90x":
  {
    "dayIcon": "cw",
    "nightIcon": "cw"
  },
   "9xx":
  {
    "dayIcon": "sw",
    "nightIcon": "mw"
  }
}
